Gestor_CSprog87-1.0.0.data/scripts/config.py
Gestor_CSprog87-1.0.0.data/scripts/database.py
Gestor_CSprog87-1.0.0.data/scripts/helpers.py
Gestor_CSprog87-1.0.0.data/scripts/menu.py
Gestor_CSprog87-1.0.0.data/scripts/run.py
Gestor_CSprog87-1.0.0.data/scripts/ui.py
tests/__init__.py
tests/test_database.py
Gestor_CSprog87-1.0.0.dist-info/LICENSE
Gestor_CSprog87-1.0.0.dist-info/METADATA
Gestor_CSprog87-1.0.0.dist-info/WHEEL
Gestor_CSprog87-1.0.0.dist-info/top_level.txt
Gestor_CSprog87-1.0.0.dist-info/RECORD
