Metadata-Version: 2.1
Name: Gestor-CSprog87
Version: 1.0.0
Summary: Gestor para una base de datos de clientes con fichero .csv
Home-page: https://github.com/CSprog87
Author: Camilo Andres Sanabria - CSprog87
Author-email: csmarketing.global@gmail.com
License-File: LICENSE
Requires-Dist: pytest
